MANIFEST.in
README.md
bazoul.py
setup.py
bazoul.egg-info/PKG-INFO
bazoul.egg-info/SOURCES.txt
bazoul.egg-info/dependency_links.txt
bazoul.egg-info/top_level.txt