Metadata-Version: 2.1
Name: bazoul
Version: 0.1
Summary: A package that generates bills
Author: Belajdel rabek 
Author-email: belajdelmedamine@gmail.com
